ljtool/__init__.py
ljtool/converter.py
ljtool/lj_amazon/__init__.py
ljtool/lj_amazon/data_from.py
ljtool/lj_amazon/url_parse.py
ljtool/lj_db/__init__.py
ljtool/lj_headers/__init__.py
ljtool/lj_headers/headers_format.py
ljtool/lj_p/__init__.py
ljtool/lj_p/singleton.py
xlj/__init__.py
xlj/converter.py
xlj/Amazon/__init__.py
xlj/Amazon/data_from.py
xlj/Amazon/url_parse.py
xlj/Comm/__init__.py
xlj/Comm/singleton.py
xlj/Comm/Header/__init__.py
xlj/Comm/Header/headers_format.py
xlj/Comm/Time/__init__.py
xlj/Comm/Time/date_conversion.py
xlj/Db/__init__.py
xlj-0.0.6.dist-info/LICENSE
xlj-0.0.6.dist-info/METADATA
xlj-0.0.6.dist-info/WHEEL
xlj-0.0.6.dist-info/entry_points.txt
xlj-0.0.6.dist-info/top_level.txt
xlj-0.0.6.dist-info/RECORD
